tree_sitter_talon/compat.py
tree_sitter_talon/__init__.py
tree_sitter_talon/py.typed
tree_sitter_talon/internal/dynamic.pyi
tree_sitter_talon/internal/parsec.py
tree_sitter_talon/internal/binding.c
tree_sitter_talon/internal/binding.pyi
tree_sitter_talon/internal/__init__.py
tree_sitter_talon/internal/core.py
tree_sitter_talon/internal/dynamic.py
tree_sitter_talon/internal/node_types.py
tree_sitter_talon/internal/binding.cpython-37m-darwin.so
tree_sitter_talon/data/tree-sitter-talon/.npmignore
tree_sitter_talon/data/tree-sitter-talon/Cargo.toml
tree_sitter_talon/data/tree-sitter-talon/grammar.js
tree_sitter_talon/data/tree-sitter-talon/LICENSE
tree_sitter_talon/data/tree-sitter-talon/binding.gyp
tree_sitter_talon/data/tree-sitter-talon/README.md
tree_sitter_talon/data/tree-sitter-talon/.gitignore
tree_sitter_talon/data/tree-sitter-talon/package.json
tree_sitter_talon/data/tree-sitter-talon/.git
tree_sitter_talon/data/tree-sitter-talon/bumpver.toml
tree_sitter_talon/data/tree-sitter-talon/test/print-settings
tree_sitter_talon/data/tree-sitter-talon/test/print-contexts
tree_sitter_talon/data/tree-sitter-talon/test/print-commands
tree_sitter_talon/data/tree-sitter-talon/test/print-files
tree_sitter_talon/data/tree-sitter-talon/test/corpus/basic.txt
tree_sitter_talon/data/tree-sitter-talon/test/corpus/andreas-talon/files.txt
tree_sitter_talon/data/tree-sitter-talon/test/corpus/andreas-talon/settings.txt
tree_sitter_talon/data/tree-sitter-talon/test/corpus/andreas-talon/commands.txt
tree_sitter_talon/data/tree-sitter-talon/test/corpus/andreas-talon/contexts.txt
tree_sitter_talon/data/tree-sitter-talon/test/corpus/talon-axkit/files.txt
tree_sitter_talon/data/tree-sitter-talon/test/corpus/knausj_talon/files.txt
tree_sitter_talon/data/tree-sitter-talon/test/corpus/knausj_talon/settings.txt
tree_sitter_talon/data/tree-sitter-talon/test/corpus/knausj_talon/commands.txt
tree_sitter_talon-1007.3.2.0.dist-info/RECORD
tree_sitter_talon-1007.3.2.0.dist-info/LICENSE
tree_sitter_talon-1007.3.2.0.dist-info/WHEEL
tree_sitter_talon-1007.3.2.0.dist-info/METADATA
